flavuer/__init__.py
flavuer/__main__.py
flavuer/utils.py
flavuer/template/app/__init__.py
flavuer/template/app/__pycache__/__init__.cpython-38.pyc
flavuer/template/app/__pycache__/db.cpython-38.pyc
flavuer/template/app/static/js/demo.js
flavuer/template/app/templates/demo.html
flavuer/template/app/templates/layout.html
flavuer-0.0.dev1.dist-info/LICENSE
flavuer-0.0.dev1.dist-info/METADATA
flavuer-0.0.dev1.dist-info/WHEEL
flavuer-0.0.dev1.dist-info/entry_points.txt
flavuer-0.0.dev1.dist-info/top_level.txt
flavuer-0.0.dev1.dist-info/RECORD
